fixpy/__init__.py
fixpy/fixpy.py
fixpy-0.0.6.dist-info/LICENSE
fixpy-0.0.6.dist-info/METADATA
fixpy-0.0.6.dist-info/WHEEL
fixpy-0.0.6.dist-info/top_level.txt
fixpy-0.0.6.dist-info/RECORD
