Metadata-Version: 2.1
Name: fixpy
Version: 0.0.6
Summary: Simple event-driven programming
Home-page: UNKNOWN
Author: Nils Wandel
Author-email: <wandeln@cs.uni-bonn.de>
License: UNKNOWN
Project-URL: Source Code, https://github.com/aschethor/fixpy
Keywords: python,event,events,event-driven,fixed-point iteration
Platform: UNKNOWN
Classifier: Development Status :: 3 - Alpha
Classifier: Intended Audience :: Developers
Classifier: Programming Language :: Python :: 3
Classifier: Operating System :: Unix
Classifier: Operating System :: MacOS :: MacOS X
Classifier: Operating System :: Microsoft :: Windows
License-File: LICENSE
Requires-Dist: matplotlib
Requires-Dist: networkx
Requires-Dist: numpy
